MANIFEST.in
README.txt
setup.cfg
setup.py
asv_media/__init__.py
asv_media/context_processors.py
asv_media/middleware.py
asv_media/settings.py
asv_media/settings_default.py
asv_media.egg-info/PKG-INFO
asv_media.egg-info/SOURCES.txt
asv_media.egg-info/dependency_links.txt
asv_media.egg-info/not-zip-safe
asv_media.egg-info/requires.txt
asv_media.egg-info/top_level.txt
asv_media/static/lib/backbone-min.js
asv_media/static/lib/jquery-1.8.2.min.js
asv_media/static/lib/jquery.cookie.min.js
asv_media/static/lib/jquery.json.min.js
asv_media/static/lib/jquery.pjax.js
asv_media/static/lib/jquery.tinycarousel.min.js
asv_media/static/lib/json.js
asv_media/static/lib/json.min.js
asv_media/static/lib/json2.js
asv_media/static/lib/json2.min.js
asv_media/static/lib/knockback-full-stack.min.js
asv_media/static/lib/knockback.min.js
asv_media/static/lib/knockout-2.2.0.js
asv_media/static/lib/underscore-min.js
asv_media/static/lib/colorbox/colorbox.css
asv_media/static/lib/colorbox/jquery.colorbox-min.js
asv_media/static/lib/colorbox/images/border.png
asv_media/static/lib/colorbox/images/controls.png
asv_media/static/lib/colorbox/images/loading.gif
asv_media/static/lib/colorbox/images/loading_background.png
asv_media/static/lib/colorbox/images/overlay.png
asv_media/static/lib/colorbox/images/ie6/borderBottomCenter.png
asv_media/static/lib/colorbox/images/ie6/borderBottomLeft.png
asv_media/static/lib/colorbox/images/ie6/borderBottomRight.png
asv_media/static/lib/colorbox/images/ie6/borderMiddleLeft.png
asv_media/static/lib/colorbox/images/ie6/borderMiddleRight.png
asv_media/static/lib/colorbox/images/ie6/borderTopCenter.png
asv_media/static/lib/colorbox/images/ie6/borderTopLeft.png
asv_media/static/lib/colorbox/images/ie6/borderTopRight.png
asv_media/static/lib/feincms/fein_tree.css
asv_media/static/lib/feincms/fein_tree.js
asv_media/static/lib/feincms/ie_compat.js
asv_media/static/lib/feincms/style.css
asv_media/static/lib/feincms/toolbox.js
asv_media/static/lib/feincms/img/arrow-move.png
asv_media/static/lib/feincms/img/contenttypes.png
asv_media/static/lib/feincms/img/default-bg.gif
asv_media/static/lib/feincms/img/disclosure-down.png
