Metadata-Version: 1.0
Name: asv-media
Version: dev-20121101-03
Summary: 
